kooka_server/__init__.py
kooka_server/__main__.py
kooka_server/cli.py
kooka_server/distributed.py
kooka_server/logging_utils.py
kooka_server/server.py
kooka_server/api/__init__.py
kooka_server/api/models_endpoint.py
kooka_server/api/anthropic/__init__.py
kooka_server/api/anthropic/messages.py
kooka_server/api/openai/__init__.py
kooka_server/api/openai/tool_calls.py
kooka_server/distributed_server/__init__.py
kooka_server/distributed_server/constants.py
kooka_server/distributed_server/generation.py
kooka_server/distributed_server/http.py
kooka_server/distributed_server/impl.py
kooka_server/distributed_server/prompt_cache.py
kooka_server/distributed_server/state.py
kooka_server/hf_utils/__init__.py
kooka_server/hf_utils/hf_cache.py
kooka_server/mlx_utils/__init__.py
kooka_server/mlx_utils/minimax_pipeline.py
kooka_server/mlx_utils/mlx_lm_compat.py
kooka_server/mlx_utils/model_provider.py
kooka_server/mlx_utils/tokenizer_compat.py
kooka_server/mlx_utils/wired_limit.py
kooka_server/tool_fixes/__init__.py
kooka_server/tool_fixes/common.py
kooka_server/tool_fixes/minimax_m2.py
kooka_server-0.0.5.dist-info/licenses/LICENSE
kooka_server-0.0.5.dist-info/METADATA
kooka_server-0.0.5.dist-info/WHEEL
kooka_server-0.0.5.dist-info/entry_points.txt
kooka_server-0.0.5.dist-info/top_level.txt
kooka_server-0.0.5.dist-info/RECORD
