Metadata-Version: 2.4
Name: kooka-server
Version: 0.0.5
Summary: local inference web server for MLX / mlx-lm.
Author: Anchen
Requires-Python: >=3.12
License-File: LICENSE
Requires-Dist: mlx-lm==0.30.5
Provides-Extra: dev
Requires-Dist: pytest>=8.0.0; extra == "dev"
Requires-Dist: pytest-timeout>=2.3.0; extra == "dev"
Requires-Dist: requests>=2.31.0; extra == "dev"
Dynamic: license-file
